README.rst
setup.py
mwtemplates/__init__.py
mwtemplates/preprocessor.py
mwtemplates/templateeditor2.py
mwtemplates.egg-info/PKG-INFO
mwtemplates.egg-info/SOURCES.txt
mwtemplates.egg-info/dependency_links.txt
mwtemplates.egg-info/pbr.json
mwtemplates.egg-info/requires.txt
mwtemplates.egg-info/top_level.txt