Metadata-Version: 1.1
Name: mwtemplates
Version: 0.3.4
Summary: MediaWiki template parser and editor
Home-page: https://github.com/danmichaelo/mwtemplates
Author: Dan Michael Heggø
Author-email: danmichaelo@gmail.com
License: MIT
Keywords: mediawiki wikipedia
Platform: UNKNOWN
Classifier: Topic :: Text Processing :: Markup
Classifier: License :: OSI Approved :: MIT License
Classifier: Intended Audience :: Developers
Classifier: Programming Language :: Python
Classifier: Programming Language :: Python :: 2.6
Classifier: Programming Language :: Python :: 2.7
Classifier: Programming Language :: Python :: 3.2
Classifier: Programming Language :: Python :: 3.3
Classifier: Programming Language :: Python :: 3.4
